env/fanorona_env.py
env/fanorona_move.py
env/fanorona_state.py
env/utils.py
fanorona_aec-3.0.2.dist-info/LICENSE
fanorona_aec-3.0.2.dist-info/METADATA
fanorona_aec-3.0.2.dist-info/WHEEL
fanorona_aec-3.0.2.dist-info/top_level.txt
fanorona_aec-3.0.2.dist-info/RECORD
