Metadata-Version: 2.1
Name: fanorona-aec
Version: 3.0.2
Summary: A PettingZoo AECEnv implementation of the Fanorona board game.
Author-email: Abhijeet Krishnan <abhijeet.krishnan@gmail.com>
License: Copyright (c) 2023 Abhijeet Krishnan
Project-URL: Repository, https://github.com/AbhijeetKrishnan/fanorona-aec
Project-URL: Bug Tracker, https://github.com/AbhijeetKrishnan/fanorona-aec/issues
Classifier: Programming Language :: Python :: 3
Classifier: Programming Language :: Python :: 3.12
Classifier: License :: OSI Approved :: MIT License
Classifier: Operating System :: OS Independent
Requires-Python: >=3.10
License-File: LICENSE
Requires-Dist: pettingzoo
Provides-Extra: dev
Requires-Dist: pre-commit ; extra == 'dev'
Requires-Dist: pytest ; extra == 'dev'
